ffht.cpython-39-x86_64-linux-gnu.so
FFHT_unofficial-0.3.dist-info/METADATA
FFHT_unofficial-0.3.dist-info/WHEEL
FFHT_unofficial-0.3.dist-info/top_level.txt
FFHT_unofficial-0.3.dist-info/RECORD
