Metadata-Version: 2.1
Name: FFHT-unofficial
Version: 0.3
Summary: Fast implementation of the Fast Hadamard Transform (FHT)
Home-page: https://github.com/alexandre-pasco/FFHT-unofficial
Author: Alexandre Pasco
License: MIT
Keywords: fast Fourier Hadamard transform butterfly
Requires-Dist: numpy
Requires-Dist: pybind11
